fjsplib/Instance.py
fjsplib/__init__.py
fjsplib/read.py
fjsplib-0.0.2.dist-info/WHEEL
fjsplib-0.0.2.dist-info/METADATA
fjsplib-0.0.2.dist-info/RECORD
