Metadata-Version: 2.3
Name: fjsplib
Version: 0.0.2
Summary: A parser for flexible job shop scheduling instances.
Keywords: scheduling,flexible job shop scheduling,fjsp
Author: Leon Lan
Author-email: Leon Lan <l.lan@vu.nl>
License: MIT License
Classifier: Intended Audience :: Developers
Classifier: Intended Audience :: Science/Research
Classifier: Development Status :: 5 - Production/Stable
Classifier: Topic :: Software Development
Classifier: Topic :: Scientific/Engineering
Classifier: License :: OSI Approved :: MIT License
Classifier: Programming Language :: Python :: 3
Requires-Python: >=3.10
Project-URL: Repository, https://github.com/PyJobShop/FJSPLIB
